py_lance_util/api/__init__.py
py_lance_util/api/middleware/global_exception.py
py_lance_util/api/middleware/oauth.py
py_lance_util/api/router.py
py_lance_util/common/__init__.py
py_lance_util/common/response.py
py_lance_util/config/__init__.py
py_lance_util/config/config.py
py_lance_util/config/logger.py
py_lance_util/config/swagger.py
py_lance_util/config/zk_config.py
py_lance_util/db/__init__.py
py_lance_util/db/connection.py
py_lance_util/deploy/BaseDockerfile
py_lance_util/deploy/Dockerfile
py_lance_util/main.py
py_lance_util/py_practice/__init__.py
py_lance_util/py_practice/background/background.py
py_lance_util/py_practice/controller/__init__.py
py_lance_util/py_practice/controller/mail_controller.py
py_lance_util/py_practice/controller/main_controller.py
py_lance_util/py_practice/controller/mq_controller.py
py_lance_util/py_practice/controller/mysql_controller.py
py_lance_util/py_practice/controller/zk_controller.py
py_lance_util/py_practice/model/student_model.py
py_lance_util/py_practice/service/__init__.py
py_lance_util/py_practice/service/mail_service.py
py_lance_util/py_practice/service/main_service.py
py_lance_util/py_practice/service/mq_service.py
py_lance_util/py_practice/service/mysql_service.py
py_lance_util/py_practice/service/zk_service.py
py_lance_util/sh/auto_pull.sh
py_lance_util/utils/rabbitmq_util.py
py_lance_util/utils/redis_util.py
py_lance_util/utils/util_sort.py
py_lance_util/utils/zk_util.py
py_lance_util-0.1.0.dist-info/WHEEL
py_lance_util-0.1.0.dist-info/METADATA
py_lance_util-0.1.0.dist-info/RECORD
