Metadata-Version: 2.1
Name: py-lance-util
Version: 0.1.0
Summary: pytdemo
Author: feilong Chen
Author-email: chenfeilong@cloudwalk.com
Requires-Python: >=3.9,<4.0
Classifier: Programming Language :: Python :: 3
Classifier: Programming Language :: Python :: 3.9
Classifier: Programming Language :: Python :: 3.10
Classifier: Programming Language :: Python :: 3.11
Requires-Dist: fastapi (==0.88.0)
Requires-Dist: kazoo (>=2.9.0,<3.0.0)
Requires-Dist: loguru (==0.6.0)
Requires-Dist: pika (==1.3.1)
Requires-Dist: pydantic (==1.9.0)
Requires-Dist: pymysql (>=1.0.2,<2.0.0)
Requires-Dist: redis (==4.4.0)
Requires-Dist: sqlalchemy (==1.4.32)
Requires-Dist: uvicorn (==0.17.6)
